devremind1/__init__.py
devremind1/__main__.py
devremind1/alarm.mp3
devremind1/remind.py
devremind1-0.1.3.dist-info/licenses/LICENSE
devremind1-0.1.3.dist-info/METADATA
devremind1-0.1.3.dist-info/WHEEL
devremind1-0.1.3.dist-info/entry_points.txt
devremind1-0.1.3.dist-info/top_level.txt
devremind1-0.1.3.dist-info/RECORD
