Metadata-Version: 2.4
Name: devremind1
Version: 0.1.3
Summary: A Python package that reminds developers to take breaks
Author: Anil Thapa
Author-email: anilthapa4200@gmail.com
License-File: LICENSE
Requires-Dist: plyer
Requires-Dist: playsound
Requires-Dist: importlib_resources; python_version < "3.9"
Dynamic: author
Dynamic: author-email
Dynamic: license-file
Dynamic: requires-dist
Dynamic: summary
